experiment_notification/__init__.py
experiment_notification/experiment_notification.py
experiment_notification-0.1.1.dist-info/METADATA
experiment_notification-0.1.1.dist-info/WHEEL
experiment_notification-0.1.1.dist-info/top_level.txt
experiment_notification-0.1.1.dist-info/RECORD
